[{"reviewerID":"A12GQ13UI7AAD2","asin":"0784011648","title":"On Golden Pond","prediction":4.0020066163},{"reviewerID":"A12GQ13UI7AAD2","asin":"0783227272","title":"Amistad VHS","prediction":3.8977385666},{"reviewerID":"A12GQ13UI7AAD2","asin":"0783116926","title":"The Changeling","prediction":3.7690973102},{"reviewerID":"A12GQ13UI7AAD2","asin":"0783239408","title":"Belleza Americana American Beauty  VHS","prediction":3.5548341291},{"reviewerID":"A12GQ13UI7AAD2","asin":"0005119367","title":"Joseph VHS","prediction":3.4752337452},{"reviewerID":"A12GQ13UI7AAD2","asin":"0783114907","title":"Sweet Dreams","prediction":3.4173554186},{"reviewerID":"A12GQ13UI7AAD2","asin":"076780192X","title":"Close Encounters of the Third Kind VHS","prediction":3.3105472135},{"reviewerID":"A12GQ13UI7AAD2","asin":"0738920762","title":"Sesame Street: 123 Count With Me","prediction":3.2615518822},{"reviewerID":"A12GQ13UI7AAD2","asin":"0783243499","title":"American Psycho VHS","prediction":3.2557877742},{"reviewerID":"A12GQ13UI7AAD2","asin":"0740318764","title":"Discovering America's Founders","prediction":3.2459899907}]