[{"reviewerID":"A2DEM6M968TEFJ","asin":"0782010792","title":"Christmas Collector's Pack The Bells of St. Mary's \/ It's a Wonderful Life","prediction":2.7281534679},{"reviewerID":"A2DEM6M968TEFJ","asin":"0767809254","title":"Steel Magnolias VHS","prediction":2.7202046187},{"reviewerID":"A2DEM6M968TEFJ","asin":"0767815335","title":"The Last Action Hero VHS","prediction":2.6863698064},{"reviewerID":"A2DEM6M968TEFJ","asin":"0767020294","title":"Jane Eyre","prediction":2.6823635068},{"reviewerID":"A2DEM6M968TEFJ","asin":"0783234287","title":"The Mummy VHS","prediction":2.6645151479},{"reviewerID":"A2DEM6M968TEFJ","asin":"0783228686","title":"Black Dog","prediction":2.6634284689},{"reviewerID":"A2DEM6M968TEFJ","asin":"0005019281","title":"An American Christmas Carol VHS","prediction":2.6613962838},{"reviewerID":"A2DEM6M968TEFJ","asin":"0767811089","title":"The Fisher King","prediction":2.66071171},{"reviewerID":"A2DEM6M968TEFJ","asin":"0783229747","title":"One True Thing VHS","prediction":2.6594206855},{"reviewerID":"A2DEM6M968TEFJ","asin":"0782008372","title":"Highlander: Director's Cut","prediction":2.6592930071}]