[{"reviewerID":"A2JP0URFHXP6DO","asin":"0767817664","title":"Fright Night","prediction":3.2561028266},{"reviewerID":"A2JP0URFHXP6DO","asin":"0783225857","title":"To Kill a Mockingbird","prediction":3.1765797144},{"reviewerID":"A2JP0URFHXP6DO","asin":"078322687X","title":"The Breakfast Club","prediction":3.1211168821},{"reviewerID":"A2JP0URFHXP6DO","asin":"0783239408","title":"Belleza Americana American Beauty  VHS","prediction":3.1106202317},{"reviewerID":"A2JP0URFHXP6DO","asin":"0767824555","title":"Hard Times","prediction":3.0598346267},{"reviewerID":"A2JP0URFHXP6DO","asin":"0780621956","title":"Wag the Dog VHS","prediction":3.0367864305},{"reviewerID":"A2JP0URFHXP6DO","asin":"0767834739","title":"Resident Evil: Apocalypse","prediction":2.9927488718},{"reviewerID":"A2JP0URFHXP6DO","asin":"0767087372","title":"Upstairs Downstairs Complete Series A&amp;E","prediction":2.9924318292},{"reviewerID":"A2JP0URFHXP6DO","asin":"0783239955","title":"The Dinner Game","prediction":2.9857746141},{"reviewerID":"A2JP0URFHXP6DO","asin":"0783226896","title":"For Richer or Poorer","prediction":2.9801238739}]