[{"reviewerID":"A3IQA3VVDHGAK1","asin":"0782010792","title":"Christmas Collector's Pack The Bells of St. Mary's \/ It's a Wonderful Life","prediction":2.709149461},{"reviewerID":"A3IQA3VVDHGAK1","asin":"0767809254","title":"Steel Magnolias VHS","prediction":2.6988832433},{"reviewerID":"A3IQA3VVDHGAK1","asin":"0780020715","title":"Beauty and The Beast The Criterion Collection","prediction":2.6824375886},{"reviewerID":"A3IQA3VVDHGAK1","asin":"0767818105","title":"Roxanne","prediction":2.6726978018},{"reviewerID":"A3IQA3VVDHGAK1","asin":"0783226985","title":"Dragon: The Bruce Lee Story","prediction":2.6674727851},{"reviewerID":"A3IQA3VVDHGAK1","asin":"0767830555","title":"Taxi Driver","prediction":2.6614671713},{"reviewerID":"A3IQA3VVDHGAK1","asin":"0783228686","title":"Black Dog","prediction":2.6558008532},{"reviewerID":"A3IQA3VVDHGAK1","asin":"0767821408","title":"Bottle Rocket","prediction":2.654180923},{"reviewerID":"A3IQA3VVDHGAK1","asin":"0780622383","title":"Dolores Claiborne VHS","prediction":2.6541348416},{"reviewerID":"A3IQA3VVDHGAK1","asin":"0784013470","title":"Stir Of Echoes","prediction":2.653609336}]