[{"reviewerID":"A3J9LLWHZH15HG","asin":"0767809254","title":"Steel Magnolias VHS","prediction":3.1545823639},{"reviewerID":"A3J9LLWHZH15HG","asin":"0780622383","title":"Dolores Claiborne VHS","prediction":3.1380965357},{"reviewerID":"A3J9LLWHZH15HG","asin":"0783114907","title":"Sweet Dreams","prediction":3.1142177965},{"reviewerID":"A3J9LLWHZH15HG","asin":"0767001311","title":"The Very Best of the Bob Newhart Show 6 VHS","prediction":3.1122585581},{"reviewerID":"A3J9LLWHZH15HG","asin":"0782010792","title":"Christmas Collector's Pack The Bells of St. Mary's \/ It's a Wonderful Life","prediction":3.1035387187},{"reviewerID":"A3J9LLWHZH15HG","asin":"076780192X","title":"Close Encounters of the Third Kind VHS","prediction":3.1001075191},{"reviewerID":"A3J9LLWHZH15HG","asin":"0780621832","title":"She Wore a Yellow Ribbon VHS","prediction":3.0807646733},{"reviewerID":"A3J9LLWHZH15HG","asin":"0783226896","title":"For Richer or Poorer","prediction":3.075672489},{"reviewerID":"A3J9LLWHZH15HG","asin":"0780020715","title":"Beauty and The Beast The Criterion Collection","prediction":3.0721000082},{"reviewerID":"A3J9LLWHZH15HG","asin":"0780621956","title":"Wag the Dog VHS","prediction":3.0640255575}]