[{"reviewerID":"A5WC1GP8XCVD","asin":"0767830555","title":"Taxi Driver","prediction":3.2565768955},{"reviewerID":"A5WC1GP8XCVD","asin":"0767834739","title":"Resident Evil: Apocalypse","prediction":3.068954184},{"reviewerID":"A5WC1GP8XCVD","asin":"078322995X","title":"The Prince of Egypt VHS","prediction":3.0175356974},{"reviewerID":"A5WC1GP8XCVD","asin":"0767836359","title":"A River Runs Through It","prediction":2.9905022414},{"reviewerID":"A5WC1GP8XCVD","asin":"0783239408","title":"Belleza Americana American Beauty  VHS","prediction":2.9646369363},{"reviewerID":"A5WC1GP8XCVD","asin":"0005119367","title":"Joseph VHS","prediction":2.9460288178},{"reviewerID":"A5WC1GP8XCVD","asin":"0783230346","title":"The Eiger Sanction","prediction":2.9410826328},{"reviewerID":"A5WC1GP8XCVD","asin":"0767821408","title":"Bottle Rocket","prediction":2.935993831},{"reviewerID":"A5WC1GP8XCVD","asin":"0767817486","title":"Midnight Express","prediction":2.9308214588},{"reviewerID":"A5WC1GP8XCVD","asin":"078322561X","title":"Babe - Pig in the City VHS","prediction":2.922221691}]