[{"reviewerID":"ALUD6AX5RPWGX","asin":"0782010792","title":"Christmas Collector's Pack The Bells of St. Mary's \/ It's a Wonderful Life","prediction":3.2580606562},{"reviewerID":"ALUD6AX5RPWGX","asin":"0005019281","title":"An American Christmas Carol VHS","prediction":3.1140264147},{"reviewerID":"ALUD6AX5RPWGX","asin":"0767815335","title":"The Last Action Hero VHS","prediction":3.0648945958},{"reviewerID":"ALUD6AX5RPWGX","asin":"0788857746","title":"Flightplan","prediction":3.0401289332},{"reviewerID":"ALUD6AX5RPWGX","asin":"0783226853","title":"The Day of the Jackal","prediction":3.0112455821},{"reviewerID":"ALUD6AX5RPWGX","asin":"0767809254","title":"Steel Magnolias VHS","prediction":2.9871471613},{"reviewerID":"ALUD6AX5RPWGX","asin":"0767811089","title":"The Fisher King","prediction":2.9790557595},{"reviewerID":"ALUD6AX5RPWGX","asin":"0782008372","title":"Highlander: Director's Cut","prediction":2.9745500593},{"reviewerID":"ALUD6AX5RPWGX","asin":"0767020294","title":"Jane Eyre","prediction":2.949320161},{"reviewerID":"ALUD6AX5RPWGX","asin":"0783112750","title":"When Trumpets Fade VHS","prediction":2.9457977854}]